AlyiosWindowsFunctions/DialogHelper.cs
AlyiosWindowsFunctions/DialogHelper.exe
AlyiosWindowsFunctions/__init__.py
AlyiosWindowsFunctions/app.manifest
AlyiosWindowsFunctions/build_helper.ps1
AlyiosWindowsFunctions/console.py
AlyiosWindowsFunctions/dialogs.py
AlyiosWindowsFunctions/inputs.py
alyios_windows-0.1.0.dist-info/licenses/LICENSE
alyios_windows-0.1.0.dist-info/METADATA
alyios_windows-0.1.0.dist-info/WHEEL
alyios_windows-0.1.0.dist-info/top_level.txt
alyios_windows-0.1.0.dist-info/RECORD
